gitlab_scripts/__init__.py
gitlab_scripts/__main__.py
gitlab_scripts/gitlab.py
gitlab_scripts/lexer.py
gitlab_scripts/project_badge/__init__.py
gitlab_scripts/project_badge/duplicate.py
gitlab_scripts/runner/__init__.py
gitlab_scripts/runner/delete.py
gitlab_scripts/runner/list.py
gitlab_scripts-1.0.1.dist-info/LICENSE
gitlab_scripts-1.0.1.dist-info/METADATA
gitlab_scripts-1.0.1.dist-info/WHEEL
gitlab_scripts-1.0.1.dist-info/entry_points.txt
gitlab_scripts-1.0.1.dist-info/top_level.txt
gitlab_scripts-1.0.1.dist-info/zip-safe
gitlab_scripts-1.0.1.dist-info/RECORD
